{"pixiv_pic": [{"name": "121496311", "path": "./pixiv/2024-08-17-14-06-45/121496311.jpg", "index": 0, "user": "Matcha_", "ext": ".jpg"}, {"name": "121493886", "path": "./pixiv/2024-08-17-14-06-45/121493886.jpg", "index": 1, "user": "\u3055\u307e\u3066\u308b", "ext": ".jpg"}, {"name": "121523921", "path": "./pixiv/2024-08-17-14-06-45/121523921.jpg", "index": 2, "user": "Roha", "ext": ".jpg"}, {"name": "121493885", "path": "./pixiv/2024-08-17-14-06-45/121493885.jpg", "index": 3, "user": "\u3086\u306b\uff0a", "ext": ".jpg"}, {"name": "121501233", "path": "./pixiv/2024-08-17-14-06-45/121501233.jpg", "index": 4, "user": "\u3042\u3089\u3082\u3093", "ext": ".jpg"}, {"name": "121493973", "path": "./pixiv/2024-08-17-14-06-45/121493973.jpg", "index": 5, "user": "\u30b1\u30fc\u30b9\u30ef\u30d9\u3010K-SUWABE\u3011", "ext": ".jpg"}, {"name": "121508910", "path": "./pixiv/2024-08-17-14-06-45/121508910.png", "index": 6, "user": "Vardan", "ext": ".png"}, {"name": "121531137", "path": "./pixiv/2024-08-17-14-06-45/121531137.jpg", "index": 7, "user": "Toy(e)", "ext": ".jpg"}, {"name": "121496744", "path": "./pixiv/2024-08-17-14-06-45/121496744.jpg", "index": 8, "user": "\u306f\u308b", "ext": ".jpg"}, {"name": "121538994", "path": "./pixiv/2024-08-17-14-06-45/121538994.jpg", "index": 9, "user": "\u3057\u3065", "ext": ".jpg"}, {"name": "121536575", "path": "./pixiv/2024-08-17-14-06-45/121536575.png", "index": 10, "user": "\u30cf\u30df\u30bf", "ext": ".png"}, {"name": "121525173", "path": "./pixiv/2024-08-17-14-06-45/121525173.jpg", "index": 11, "user": "Rella", "ext": ".jpg"}, {"name": "121506139", "path": "./pixiv/2024-08-17-14-06-45/121506139.png", "index": 12, "user": "\u3057\u3065", "ext": ".png"}, {"name": "121516898", "path": "./pixiv/2024-08-17-14-06-45/121516898.jpg", "index": 13, "user": "\u306e\u3046", "ext": ".jpg"}, {"name": "121544843", "path": "./pixiv/2024-08-17-14-06-45/121544843.jpg", "index": 14, "user": "\u30ce\u30fc\u30b3\u30d4\u30fc\u30e9\u30a4\u30c8\u30ac\u30fc\u30eb", "ext": ".jpg"}, {"name": "121522032", "path": "./pixiv/2024-08-17-14-06-45/121522032.jpg", "index": 15, "user": "Saclia", "ext": ".jpg"}, {"name": "121525364", "path": "./pixiv/2024-08-17-14-06-45/121525364.jpg", "index": 16, "user": "\u304b\u3081\u3071\u3059\u305f", "ext": ".jpg"}, {"name": "121507481", "path": "./pixiv/2024-08-17-14-06-45/121507481.jpg", "index": 17, "user": "3sai", "ext": ".jpg"}, {"name": "121508353", "path": "./pixiv/2024-08-17-14-06-45/121508353.jpg", "index": 18, "user": "\u306f\u3068\u307c\u3057", "ext": ".jpg"}, {"name": "121496608", "path": "./pixiv/2024-08-17-14-06-45/121496608.jpg", "index": 19, "user": "Solipsist", "ext": ".jpg"}, {"name": "121541807", "path": "./pixiv/2024-08-17-14-06-45/121541807.jpg", "index": 20, "user": "\u4eca\u65e5\u306e\u6669\u3054\u98ef\u306f", "ext": ".jpg"}, {"name": "121532932", "path": "./pixiv/2024-08-17-14-06-45/121532932.png", "index": 21, "user": "\u5927\u6d25", "ext": ".png"}, {"name": "121505724", "path": "./pixiv/2024-08-17-14-06-45/121505724.png", "index": 22, "user": "\u80e1\u9ebb\u4e43\u308a\u304a", "ext": ".png"}, {"name": "121502730", "path": "./pixiv/2024-08-17-14-06-45/121502730.png", "index": 23, "user": "\u30ef\u30fc\u30ef\u30fc\u8a00\u3046\u3068\u308a\u307e\u52a9\u2103", "ext": ".png"}, {"name": "121495068", "path": "./pixiv/2024-08-17-14-06-45/121495068.jpg", "index": 24, "user": "\u304b\u3081\u3071\u3059\u305f", "ext": ".jpg"}, {"name": "121494242", "path": "./pixiv/2024-08-17-14-06-45/121494242.png", "index": 25, "user": "Lowro", "ext": ".png"}, {"name": "121509043", "path": "./pixiv/2024-08-17-14-06-45/121509043.jpg", "index": 26, "user": "Silver", "ext": ".jpg"}, {"name": "121536355", "path": "./pixiv/2024-08-17-14-06-45/121536355.jpg", "index": 27, "user": "\u8f9b\u53e3\u30e0\u30fc\u30b9", "ext": ".jpg"}, {"name": "121505929", "path": "./pixiv/2024-08-17-14-06-45/121505929.png", "index": 28, "user": "Mors", "ext": ".png"}, {"name": "121516174", "path": "./pixiv/2024-08-17-14-06-45/121516174.png", "index": 29, "user": "\u304a\u304a\u307f\u3084", "ext": ".png"}, {"name": "121517043", "path": "./pixiv/2024-08-17-14-06-45/121517043.png", "index": 30, "user": "4B\u925b\u7b46", "ext": ".png"}, {"name": "121493961", "path": "./pixiv/2024-08-17-14-06-45/121493961.jpg", "index": 31, "user": "siki", "ext": ".jpg"}, {"name": "121525398", "path": "./pixiv/2024-08-17-14-06-45/121525398.jpg", "index": 32, "user": "\u6708\u591c", "ext": ".jpg"}, {"name": "121552795", "path": "./pixiv/2024-08-17-14-06-45/121552795.jpg", "index": 33, "user": "\u3059\u3073\u304b\u304b", "ext": ".jpg"}, {"name": "121515156", "path": "./pixiv/2024-08-17-14-06-45/121515156.jpg", "index": 34, "user": "\u9752\u4e95\u3055\u3081@\u30b3\u30df\u30b1\u65e5\u66dc\u897f\u306a19b", "ext": ".jpg"}, {"name": "121535216", "path": "./pixiv/2024-08-17-14-06-45/121535216.png", "index": 35, "user": "Csyday", "ext": ".png"}, {"name": "121529093", "path": "./pixiv/2024-08-17-14-06-45/121529093.png", "index": 36, "user": "\u30ef\u30fc\u30ef\u30fc\u8a00\u3046\u3068\u308a\u307e\u52a9\u2103", "ext": ".png"}, {"name": "121493829", "path": "./pixiv/2024-08-17-14-06-45/121493829.jpg", "index": 37, "user": "Lifeline", "ext": ".jpg"}, {"name": "121526469", "path": "./pixiv/2024-08-17-14-06-45/121526469.jpg", "index": 38, "user": "\u5b97\u5b5d", "ext": ".jpg"}]}